<?xml version="1.0" encoding="UTF-8"?><CancelaCFDResponse xmlns="http://cancelacfd.sat.gob.mx"><CancelaCFDResult Fecha="2018-09-28T10:57:58.3229637" RfcEmisor="RLA180323GQ1"><Folios><UUID>5B1D7EEC-024A-43BC-8544-E1D3C0343221</UUID><EstatusUUID>201</EstatusUUID></Folios><Signature xmlns="http://www.w3.org/2000/09/xmldsig#" Id="SelloSAT"><SignedInfo><CanonicalizationMethod Algorithm="http://www.w3.org/TR/2001/REC-xml-c14n-20010315"/><SignatureMethod Algorithm="http://www.w3.org/2001/04/xmldsig-more#hmac-sha512"/><Reference URI=""><Transforms><Transform Algorithm="http://www.w3.org/TR/1999/REC-xpath-19991116"><XPath>not(ancestor-or-self::*[local-name()='Signature'])</XPath></Transform></Transforms><DigestMethod Algorithm="http://www.w3.org/2001/04/xmlenc#sha512"/><DigestValue>6MHbiiSUyg311KGwTGMPdcGrdhh7gtS6klm84ZVNXqvks71thxmU6oSMb16o4K0QsTSwbgVYtloqnXQbBzH0mw==</DigestValue></Reference></SignedInfo><SignatureValue>8GCWxy+gjE8G3DZk7DsQxEBR0f520g/ifdiqfluW2df9wsYk+/qoVnXLhmltzJtBKtTEWyLUGN6jtZplOV6GrA==</SignatureValue><KeyInfo><KeyName>00001088888800000016</KeyName><KeyValue><RSAKeyValue><Modulus>xnL2zDPtH5jDsAZDTIfMqbKGrve+At8Kyx2EZvbfXbpK9uVExWS874oMelFzNq69/YqSReT3I7I8wr+joy5O7ouZH+4KWdIGp4Si6lHe0kntxzNmuuKyOPkJ9tMcntnFmQ4bfxFxlg/Ud2hCtuoy3j2xYkIXu5O4pGM98Nz8pAM=</Modulus><Exponent>AQAB</Exponent></RSAKeyValue></KeyValue></KeyInfo></Signature></CancelaCFDResult></CancelaCFDResponse>